titanic/__init__.py
titanic/cli.py
titanic/store.py
titanic/sync.py
titanic/utils.py
titanic_syncer-0.3.10.dist-info/METADATA
titanic_syncer-0.3.10.dist-info/WHEEL
titanic_syncer-0.3.10.dist-info/entry_points.txt
titanic_syncer-0.3.10.dist-info/RECORD
